Metadata-Version: 2.1
Name: linear-congruential-generator
Version: 0.1.3
Summary: The random number generator. 
Home-page: https://github.com/onuratakan/LCG
Author: Onur Atakan ULUSOY
Author-email: atadogan06@gmail.com
License: MIT
Platform: UNKNOWN
Requires-Python: >=3.0
